{
  "collectionName": "components_home_home_after_heroes",
  "info": {
    "displayName": "HomeAfterHero"
  },
  "options": {},
  "attributes": {
    "AfterHeroTitle": {
      "type": "text"
    },
    "AfterHeroTurningImg": {
      "allowedTypes": [
        "images",
        "files"
      ],
      "type": "media",
      "multiple": false
    },
    "StradaImage": {
      "allowedTypes": [
        "images",
        "files"
      ],
      "type": "media",
      "multiple": false
    },
    "SpotImage": {
      "allowedTypes": [
        "images",
        "files"
      ],
      "type": "media",
      "multiple": false
    },
    "CambridgeImage": {
      "allowedTypes": [
        "images",
        "files"
      ],
      "type": "media",
      "multiple": false
    },
    "UteesImage": {
      "allowedTypes": [
        "images",
        "files"
      ],
      "type": "media",
      "multiple": false
    },
    "RulaImage": {
      "allowedTypes": [
        "images",
        "files"
      ],
      "type": "media",
      "multiple": false
    }
  }
}
